{"total_meldingen": 1802, "total_resolved": 1412, "total_dates": 43, "first_date": "2026-05-18", "last_date": "2026-06-29", "daily_counts": {"2026-05-18": {"wegen-verkeer-en-straatmeubilair": 139, "afval": 29, "openbaar-groen-en-water": 43, "overlast-openbare-ruimte": 46, "riolering": 3, "overlast-dier": 18}, "2026-05-19": {"afval": 27, "wegen-verkeer-en-straatmeubilair": 140, "overlast-openbare-ruimte": 47, "overig": 1, "overlast-dier": 18, "openbaar-groen-en-water": 40, "civiele-constructie": 1, "riolering": 3}, "2026-05-20": {"wegen-verkeer-en-straatmeubilair": 135, "overig": 4, "openbaar-groen-en-water": 39, "afval": 21, "overlast-openbare-ruimte": 44, "overlast-dier": 16, "riolering": 4}, "2026-05-21": {"wegen-verkeer-en-straatmeubilair": 142, "afval": 29, "openbaar-groen-en-water": 35, "riolering": 4, "overlast-openbare-ruimte": 45, "overlast-dier": 16}, "2026-05-22": {"wegen-verkeer-en-straatmeubilair": 138, "openbaar-groen-en-water": 30, "afval": 26, "overlast-openbare-ruimte": 42, "overlast-dier": 16, "riolering": 3}, "2026-05-23": {"overig": 1, "afval": 26, "overlast-openbare-ruimte": 43, "wegen-verkeer-en-straatmeubilair": 139, "overlast-dier": 19, "openbaar-groen-en-water": 31, "riolering": 3}, "2026-05-24": {"wegen-verkeer-en-straatmeubilair": 142, "afval": 29, "overlast-openbare-ruimte": 45, "openbaar-groen-en-water": 34, "overig": 3, "overlast-dier": 20, "riolering": 3}, "2026-05-25": {"overlast-openbare-ruimte": 52, "wegen-verkeer-en-straatmeubilair": 145, "overlast-dier": 22, "afval": 30, "openbaar-groen-en-water": 34, "overig": 3, "riolering": 3}, "2026-05-26": {"afval": 30, "wegen-verkeer-en-straatmeubilair": 147, "openbaar-groen-en-water": 40, "overlast-openbare-ruimte": 54, "overlast-dier": 23, "riolering": 4}, "2026-05-27": {"afval": 40, "wegen-verkeer-en-straatmeubilair": 119, "openbaar-groen-en-water": 52, "overlast-openbare-ruimte": 60, "overlast-dier": 28, "riolering": 3}, "2026-05-28": {"afval": 32, "openbaar-groen-en-water": 55, "wegen-verkeer-en-straatmeubilair": 112, "overlast-openbare-ruimte": 58, "overlast-dier": 23, "civiele-constructie": 1, "riolering": 3}, "2026-05-29": {"afval": 42, "wegen-verkeer-en-straatmeubilair": 108, "openbaar-groen-en-water": 52, "overlast-openbare-ruimte": 63, "civiele-constructie": 2, "overlast-dier": 20, "riolering": 3}, "2026-05-30": {"afval": 36, "openbaar-groen-en-water": 62, "wegen-verkeer-en-straatmeubilair": 113, "riolering": 6, "overlast-dier": 26, "overig": 2, "overlast-openbare-ruimte": 66, "civiele-constructie": 2}, "2026-05-31": {"afval": 38, "overlast-openbare-ruimte": 62, "overig": 3, "wegen-verkeer-en-straatmeubilair": 116, "riolering": 7, "openbaar-groen-en-water": 66, "overlast-dier": 26, "civiele-constructie": 2}, "2026-06-01": {"overlast-openbare-ruimte": 66, "afval": 37, "wegen-verkeer-en-straatmeubilair": 112, "openbaar-groen-en-water": 74, "overlast-dier": 27, "riolering": 4, "civiele-constructie": 2}, "2026-06-02": {"overlast-openbare-ruimte": 69, "wegen-verkeer-en-straatmeubilair": 116, "openbaar-groen-en-water": 84, "afval": 29, "overlast-dier": 29, "riolering": 4, "civiele-constructie": 2}, "2026-06-03": {"openbaar-groen-en-water": 82, "overlast-openbare-ruimte": 72, "overlast-dier": 29, "wegen-verkeer-en-straatmeubilair": 121, "afval": 31, "civiele-constructie": 2, "riolering": 3}, "2026-06-04": {"openbaar-groen-en-water": 78, "afval": 28, "wegen-verkeer-en-straatmeubilair": 118, "overlast-dier": 26, "overlast-openbare-ruimte": 66, "riolering": 4, "civiele-constructie": 2}, "2026-06-05": {"openbaar-groen-en-water": 79, "riolering": 8, "afval": 28, "overlast-openbare-ruimte": 63, "wegen-verkeer-en-straatmeubilair": 116, "overlast-dier": 25, "civiele-constructie": 2}, "2026-06-06": {"overlast-openbare-ruimte": 65, "openbaar-groen-en-water": 72, "afval": 28, "wegen-verkeer-en-straatmeubilair": 122, "overig": 3, "riolering": 3, "overlast-dier": 24, "civiele-constructie": 2}, "2026-06-07": {"afval": 32, "openbaar-groen-en-water": 79, "wegen-verkeer-en-straatmeubilair": 128, "overlast-openbare-ruimte": 62, "overlast-dier": 25, "overig": 4, "riolering": 3, "civiele-constructie": 2}, "2026-06-08": {"overlast-openbare-ruimte": 58, "afval": 34, "openbaar-groen-en-water": 70, "overlast-dier": 29, "wegen-verkeer-en-straatmeubilair": 128, "riolering": 3, "civiele-constructie": 2}, "2026-06-09": {"afval": 47, "wegen-verkeer-en-straatmeubilair": 126, "overlast-dier": 29, "openbaar-groen-en-water": 76, "riolering": 4, "overlast-openbare-ruimte": 60, "civiele-constructie": 1}, "2026-06-10": {"openbaar-groen-en-water": 85, "afval": 40, "wegen-verkeer-en-straatmeubilair": 113, "riolering": 6, "overlast-openbare-ruimte": 46, "overlast-dier": 24, "civiele-constructie": 1}, "2026-06-11": {"afval": 56, "wegen-verkeer-en-straatmeubilair": 117, "openbaar-groen-en-water": 95, "overlast-openbare-ruimte": 46, "riolering": 4, "overlast-dier": 22, "civiele-constructie": 1}, "2026-06-12": {"afval": 55, "wegen-verkeer-en-straatmeubilair": 115, "overlast-openbare-ruimte": 48, "openbaar-groen-en-water": 102, "riolering": 6, "overig": 1, "overlast-dier": 20, "civiele-constructie": 1}, "2026-06-13": {"afval": 36, "openbaar-groen-en-water": 106, "wegen-verkeer-en-straatmeubilair": 117, "overlast-openbare-ruimte": 47, "overig": 1, "riolering": 5, "overlast-dier": 20, "civiele-constructie": 1}, "2026-06-14": {"afval": 38, "openbaar-groen-en-water": 108, "overig": 3, "wegen-verkeer-en-straatmeubilair": 125, "overlast-openbare-ruimte": 49, "overlast-dier": 22, "riolering": 5, "civiele-constructie": 1}, "2026-06-15": {"afval": 41, "wegen-verkeer-en-straatmeubilair": 117, "overlast-dier": 24, "overlast-openbare-ruimte": 50, "openbaar-groen-en-water": 98, "overig": 2, "riolering": 5, "civiele-constructie": 1}, "2026-06-16": {"openbaar-groen-en-water": 85, "wegen-verkeer-en-straatmeubilair": 116, "afval": 40, "overlast-dier": 23, "overlast-openbare-ruimte": 47, "overig": 1, "riolering": 4, "civiele-constructie": 1}, "2026-06-17": {"wegen-verkeer-en-straatmeubilair": 117, "afval": 59, "openbaar-groen-en-water": 90, "riolering": 5, "overlast-openbare-ruimte": 51, "overlast-dier": 20, "overig": 2, "civiele-constructie": 1}, "2026-06-18": {"afval": 44, "overlast-openbare-ruimte": 50, "wegen-verkeer-en-straatmeubilair": 117, "overlast-dier": 20, "overig": 2, "openbaar-groen-en-water": 87, "civiele-constructie": 2, "riolering": 4}, "2026-06-19": {"afval": 42, "overlast-dier": 22, "wegen-verkeer-en-straatmeubilair": 116, "overlast-openbare-ruimte": 47, "openbaar-groen-en-water": 90, "civiele-constructie": 2, "overig": 2, "riolering": 4}, "2026-06-20": {"afval": 50, "openbaar-groen-en-water": 113, "wegen-verkeer-en-straatmeubilair": 121, "overlast-openbare-ruimte": 50, "overig": 5, "riolering": 5, "overlast-dier": 21, "civiele-constructie": 1}, "2026-06-21": {"openbaar-groen-en-water": 127, "overig": 9, "afval": 52, "wegen-verkeer-en-straatmeubilair": 122, "overlast-openbare-ruimte": 49, "riolering": 5, "overlast-dier": 21, "civiele-constructie": 1}, "2026-06-22": {"openbaar-groen-en-water": 152, "afval": 45, "overlast-dier": 26, "riolering": 6, "wegen-verkeer-en-straatmeubilair": 125, "overig": 3, "overlast-openbare-ruimte": 56, "civiele-constructie": 2}, "2026-06-23": {"openbaar-groen-en-water": 137, "wegen-verkeer-en-straatmeubilair": 131, "overlast-openbare-ruimte": 56, "afval": 43, "overlast-dier": 28, "riolering": 5, "civiele-constructie": 2, "overig": 2}, "2026-06-24": {"overlast-openbare-ruimte": 63, "openbaar-groen-en-water": 131, "afval": 47, "wegen-verkeer-en-straatmeubilair": 127, "overlast-dier": 29, "civiele-constructie": 2, "overig": 2, "riolering": 3}, "2026-06-25": {"overig": 3, "afval": 47, "wegen-verkeer-en-straatmeubilair": 128, "openbaar-groen-en-water": 113, "overlast-dier": 29, "overlast-openbare-ruimte": 61, "civiele-constructie": 2, "riolering": 3}, "2026-06-26": {"afval": 48, "openbaar-groen-en-water": 106, "wegen-verkeer-en-straatmeubilair": 122, "riolering": 4, "overlast-openbare-ruimte": 62, "overlast-dier": 27, "civiele-constructie": 2, "overig": 2}, "2026-06-27": {"overlast-dier": 29, "wegen-verkeer-en-straatmeubilair": 125, "afval": 52, "openbaar-groen-en-water": 110, "overlast-openbare-ruimte": 63, "civiele-constructie": 2, "overig": 2, "riolering": 3}, "2026-06-28": {"openbaar-groen-en-water": 113, "overlast-dier": 30, "wegen-verkeer-en-straatmeubilair": 127, "overlast-openbare-ruimte": 63, "afval": 55, "civiele-constructie": 2, "overig": 2, "riolering": 3}, "2026-06-29": {"openbaar-groen-en-water": 108, "overlast-openbare-ruimte": 60, "afval": 56, "wegen-verkeer-en-straatmeubilair": 128, "riolering": 4, "overig": 2, "overlast-dier": 31, "civiele-constructie": 2}}, "total_counts": {"2026-05-18": 263, "2026-05-19": 273, "2026-05-20": 263, "2026-05-21": 271, "2026-05-22": 255, "2026-05-23": 262, "2026-05-24": 276, "2026-05-25": 289, "2026-05-26": 298, "2026-05-27": 302, "2026-05-28": 284, "2026-05-29": 290, "2026-05-30": 313, "2026-05-31": 320, "2026-06-01": 322, "2026-06-02": 333, "2026-06-03": 340, "2026-06-04": 322, "2026-06-05": 321, "2026-06-06": 319, "2026-06-07": 335, "2026-06-08": 324, "2026-06-09": 343, "2026-06-10": 315, "2026-06-11": 341, "2026-06-12": 348, "2026-06-13": 333, "2026-06-14": 350, "2026-06-15": 338, "2026-06-16": 317, "2026-06-17": 345, "2026-06-18": 326, "2026-06-19": 325, "2026-06-20": 366, "2026-06-21": 386, "2026-06-22": 415, "2026-06-23": 404, "2026-06-24": 404, "2026-06-25": 386, "2026-06-26": 373, "2026-06-27": 386, "2026-06-28": 395, "2026-06-29": 391}, "categories": {"openbaar-groen-en-water": {"name": "openbaar-groen-en-water", "total": 549, "subcategories": {"openbaar-groen-en-water": {"name": "openbaar-groen-en-water", "count": 549}}}, "afval": {"name": "afval", "total": 437, "subcategories": {"afval": {"name": "afval", "count": 437}}}, "wegen-verkeer-en-straatmeubilair": {"name": "wegen-verkeer-en-straatmeubilair", "total": 427, "subcategories": {"wegen-verkeer-en-straatmeubilair": {"name": "wegen-verkeer-en-straatmeubilair", "count": 427}}}, "overlast-openbare-ruimte": {"name": "overlast-openbare-ruimte", "total": 208, "subcategories": {"overlast-openbare-ruimte": {"name": "overlast-openbare-ruimte", "count": 208}}}, "overlast-dier": {"name": "overlast-dier", "total": 107, "subcategories": {"overlast-dier": {"name": "overlast-dier", "count": 107}}}, "riolering": {"name": "riolering", "total": 35, "subcategories": {"riolering": {"name": "riolering", "count": 35}}}, "overig": {"name": "overig", "total": 33, "subcategories": {"overig": {"name": "overig", "count": 33}}}, "civiele-constructie": {"name": "civiele-constructie", "total": 6, "subcategories": {"civiele-constructie": {"name": "civiele-constructie", "count": 6}}}}, "hotspots": [{"lat": 52.98487, "lng": 6.58216, "count": 6}, {"lat": 52.99322, "lng": 6.5858, "count": 3}, {"lat": 53.00514, "lng": 6.50239, "count": 3}, {"lat": 53.00836, "lng": 6.53919, "count": 3}, {"lat": 53.00825, "lng": 6.51541, "count": 3}, {"lat": 53.02128, "lng": 6.58459, "count": 3}, {"lat": 53.00422, "lng": 6.53923, "count": 3}, {"lat": 53.00039, "lng": 6.54629, "count": 3}, {"lat": 52.99711, "lng": 6.55505, "count": 3}, {"lat": 52.99275, "lng": 6.56165, "count": 3}, {"lat": 52.99843, "lng": 6.55446, "count": 3}, {"lat": 52.99564, "lng": 6.56181, "count": 3}, {"lat": 52.99838, "lng": 6.5658, "count": 3}, {"lat": 53.00528, "lng": 6.53745, "count": 3}, {"lat": 53.01046, "lng": 6.56361, "count": 3}, {"lat": 53.01326, "lng": 6.55804, "count": 3}, {"lat": 52.99226, "lng": 6.57023, "count": 3}, {"lat": 52.99787, "lng": 6.55156, "count": 3}, {"lat": 52.99838, "lng": 6.56754, "count": 3}, {"lat": 53.00033, "lng": 6.50461, "count": 3}, {"lat": 52.99081, "lng": 6.53104, "count": 2}, {"lat": 52.99628, "lng": 6.5483, "count": 2}, {"lat": 53.01974, "lng": 6.60141, "count": 2}, {"lat": 53.01574, "lng": 6.56044, "count": 2}, {"lat": 53.00652, "lng": 6.54397, "count": 2}, {"lat": 52.99779, "lng": 6.55171, "count": 2}, {"lat": 53.01999, "lng": 6.56927, "count": 2}, {"lat": 53.00798, "lng": 6.55906, "count": 2}, {"lat": 53.00772, "lng": 6.55657, "count": 2}, {"lat": 52.9813, "lng": 6.59016, "count": 2}, {"lat": 53.00641, "lng": 6.56013, "count": 2}, {"lat": 53.00737, "lng": 6.55993, "count": 2}, {"lat": 53.01062, "lng": 6.56221, "count": 2}, {"lat": 52.99129, "lng": 6.5473, "count": 2}, {"lat": 53.00843, "lng": 6.54683, "count": 2}, {"lat": 52.99586, "lng": 6.56592, "count": 2}, {"lat": 52.98706, "lng": 6.57916, "count": 2}, {"lat": 53.02653, "lng": 6.56871, "count": 2}, {"lat": 53.0235, "lng": 6.56376, "count": 2}, {"lat": 52.99984, "lng": 6.50068, "count": 2}, {"lat": 52.99811, "lng": 6.5838, "count": 2}, {"lat": 53.00103, "lng": 6.51533, "count": 2}, {"lat": 53.02028, "lng": 6.55357, "count": 2}, {"lat": 52.98665, "lng": 6.57851, "count": 2}, {"lat": 52.99266, "lng": 6.54744, "count": 2}, {"lat": 53.00768, "lng": 6.51996, "count": 2}, {"lat": 52.99492, "lng": 6.51742, "count": 2}, {"lat": 53.00923, "lng": 6.53905, "count": 2}, {"lat": 53.00219, "lng": 6.5048, "count": 2}, {"lat": 52.98705, "lng": 6.57918, "count": 2}], "wijk_summary": [{"name": "Kloosterveen", "count": 299}, {"name": "Noorderpark", "count": 248}, {"name": "Centrum", "count": 232}, {"name": "Assen-Oost", "count": 221}, {"name": "Lariks", "count": 215}, {"name": "Peelo", "count": 203}, {"name": "Marsdijk", "count": 192}, {"name": "Assen-West", "count": 91}, {"name": "Buitengebied", "count": 48}, {"name": "Wijk 04 Pittelo", "count": 24}, {"name": "Wijk 19 Rolde", "count": 11}, {"name": "Wijk 21 Ekehaar", "count": 5}, {"name": "Wijk 06 Peelo", "count": 3}, {"name": "Wijk 09 Vries", "count": 2}, {"name": "Wijk 00 Assen centrum", "count": 1}, {"name": "Wijk 02 Hooghalen", "count": 1}, {"name": "Wijk 01 Lariks", "count": 1}, {"name": "Wijk 07 Bovensmilde", "count": 1}, {"name": "Wijk 08 Kloosterveen", "count": 1}, {"name": "Wijk 07 Marsdijk", "count": 1}], "resolution_stats": {"wegen-verkeer-en-straatmeubilair": {"count": 299, "avg_days": 18.2, "min_days": 0, "max_days": 156}, "afval": {"count": 382, "avg_days": 4.0, "min_days": 0, "max_days": 335}, "overlast-openbare-ruimte": {"count": 148, "avg_days": 18.4, "min_days": 0, "max_days": 384}, "openbaar-groen-en-water": {"count": 441, "avg_days": 4.8, "min_days": 0, "max_days": 97}, "riolering": {"count": 31, "avg_days": 2.5, "min_days": 0, "max_days": 34}, "overlast-dier": {"count": 76, "avg_days": 10.5, "min_days": 0, "max_days": 73}, "overig": {"count": 31, "avg_days": 1.5, "min_days": 0, "max_days": 11}, "civiele-constructie": {"count": 4, "avg_days": 4.0, "min_days": 0, "max_days": 13}}, "recent_resolved": [{"id": "efbb56bceae6889b", "lng": 6.53745414, "lat": 53.00528368, "category": "Openbaar groen en water", "category_slug": "openbaar-groen-en-water", "subcategory": "Maaien", "subcategory_slug": "maaien", "created_at": "2026-06-22T07:49:50.646984+00:00", "wijk": "Lariks", "address": "Donaustraat 37", "resolved_date": "2026-06-29", "days_open": 6}, {"id": "38bc0767de8c7dd4", "lng": 6.53637418, "lat": 53.00557266, "category": "Openbaar groen en water", "category_slug": "openbaar-groen-en-water", "subcategory": "Overig Openbaar groen en water", "subcategory_slug": "overig-openbaar-groen-en-water", "created_at": "2026-06-23T08:48:43.907613+00:00", "wijk": "Lariks", "address": "Sambrestraat 17", "resolved_date": "2026-06-29", "days_open": 5}, {"id": "b5b6fc46d49ce85f", "lng": 6.54256227, "lat": 53.004918326, "category": "Openbaar groen en water", "category_slug": "openbaar-groen-en-water", "subcategory": "Snoeien", "subcategory_slug": "snoeien", "created_at": "2026-06-20T22:37:47.103744+00:00", "wijk": "Lariks", "address": "Geulstraat 38", "resolved_date": "2026-06-29", "days_open": 8}, {"id": "7f0f813f86a2c759", "lng": 6.53958528, "lat": 53.00530809, "category": "Openbaar groen en water", "category_slug": "openbaar-groen-en-water", "subcategory": "Onkruid", "subcategory_slug": "onkruid", "created_at": "2026-06-22T19:39:12.797847+00:00", "wijk": "Lariks", "address": "Maasstraat 69", "resolved_date": "2026-06-29", "days_open": 6}, {"id": "3e1a41a2b3f2e66f", "lng": 6.545353085, "lat": 53.007406787, "category": "Openbaar groen en water", "category_slug": "openbaar-groen-en-water", "subcategory": "Boom", "subcategory_slug": "boom", "created_at": "2026-06-23T12:29:32.431036+00:00", "wijk": "Lariks", "address": "Maasstraat 34", "resolved_date": "2026-06-29", "days_open": 5}, {"id": "162bbaf2438bcf95", "lng": 6.55950864, "lat": 53.00795147, "category": "Afval", "category_slug": "afval", "subcategory": "Container", "subcategory_slug": "container", "created_at": "2026-06-26T11:51:28.769099+00:00", "wijk": "Noorderpark", "address": "Obrechtlaan 3B", "resolved_date": "2026-06-29", "days_open": 2}, {"id": "b64bb43e58a3c4a0", "lng": 6.555337893, "lat": 53.009947664, "category": "Openbaar groen en water", "category_slug": "openbaar-groen-en-water", "subcategory": "Boom", "subcategory_slug": "boom", "created_at": "2026-06-28T07:24:42.223736+00:00", "wijk": "Noorderpark", "address": "Oranjebond 10", "resolved_date": "2026-06-29", "days_open": 0}, {"id": "9ada33bf121775c2", "lng": 6.540793329, "lat": 53.007873174, "category": "Openbaar groen en water", "category_slug": "openbaar-groen-en-water", "subcategory": "Overig Openbaar groen en water", "subcategory_slug": "overig-openbaar-groen-en-water", "created_at": "2026-06-26T10:33:25.728705+00:00", "wijk": "Lariks", "address": "Elbestraat 71", "resolved_date": "2026-06-29", "days_open": 2}, {"id": "af726dcd28772811", "lng": 6.558215618, "lat": 53.016277451, "category": "Openbaar groen en water", "category_slug": "openbaar-groen-en-water", "subcategory": "Snoeien", "subcategory_slug": "snoeien", "created_at": "2026-06-15T13:55:54.90704+00:00", "wijk": "Peelo", "address": "Beuzeveen 72", "resolved_date": "2026-06-29", "days_open": 13}, {"id": "7a3380ed95726387", "lng": 6.56073928, "lat": 53.02014651, "category": "Afval", "category_slug": "afval", "subcategory": "Minicontainer", "subcategory_slug": "minicontainer", "created_at": "2026-06-26T14:19:34.036986+00:00", "wijk": "Peelo", "address": "Heklanden 31", "resolved_date": "2026-06-29", "days_open": 2}, {"id": "167bd9c5e1323ada", "lng": 6.593171655, "lat": 53.025793411, "category": "Openbaar groen en water", "category_slug": "openbaar-groen-en-water", "subcategory": "Boom", "subcategory_slug": "boom", "created_at": "2026-06-25T10:15:40.333435+00:00", "wijk": "Marsdijk", "address": "Sternmesschen 10", "resolved_date": "2026-06-29", "days_open": 3}, {"id": "4aa132dd161997cd", "lng": 6.588258256, "lat": 53.024439857, "category": "Openbaar groen en water", "category_slug": "openbaar-groen-en-water", "subcategory": "Overig Openbaar groen en water", "subcategory_slug": "overig-openbaar-groen-en-water", "created_at": "2026-06-22T17:50:46.390743+00:00", "wijk": "Marsdijk", "address": "Vlintdreef 19", "resolved_date": "2026-06-29", "days_open": 6}, {"id": "2f9aecf0a0d8c86e", "lng": 6.58227958, "lat": 53.02084987, "category": "Openbaar groen en water", "category_slug": "openbaar-groen-en-water", "subcategory": "Overig Openbaar groen en water", "subcategory_slug": "overig-openbaar-groen-en-water", "created_at": "2026-06-25T11:50:27.307992+00:00", "wijk": "Marsdijk", "address": "Jan Palachweg 33", "resolved_date": "2026-06-29", "days_open": 3}, {"id": "cff9e0b26a6367b1", "lng": 6.562997997, "lat": 53.014889843, "category": "Afval", "category_slug": "afval", "subcategory": "Minicontainer", "subcategory_slug": "minicontainer", "created_at": "2026-06-26T14:01:27.682355+00:00", "wijk": "Peelo", "address": "Koldakker 96", "resolved_date": "2026-06-29", "days_open": 2}, {"id": "131d258615b1f957", "lng": 6.57341701, "lat": 52.97709953, "category": "Afval", "category_slug": "afval", "subcategory": "Container", "subcategory_slug": "container", "created_at": "2026-06-26T12:45:47.62567+00:00", "wijk": "Assen-Oost", "address": "Middenweg 24N", "resolved_date": "2026-06-29", "days_open": 2}, {"id": "8de2ea54610224d2", "lng": 6.583617706, "lat": 52.990867088, "category": "Overlast Dier", "category_slug": "overlast-dier", "subcategory": "Hond", "subcategory_slug": "hond", "created_at": "2026-06-28T06:47:54.070121+00:00", "wijk": "Assen-Oost", "address": "Platolaan 1", "resolved_date": "2026-06-29", "days_open": 0}, {"id": "19d99d10fca2d88f", "lng": 6.563514263, "lat": 52.991850817, "category": "Overlast Openbare Ruimte", "category_slug": "overlast-openbare-ruimte", "subcategory": "Overig Overlast Openbare Ruimte", "subcategory_slug": "overig-overlast-openbare-ruimte", "created_at": "2026-05-25T00:31:05.499897+00:00", "wijk": "Centrum", "address": "Zuidersingel 49", "resolved_date": "2026-06-29", "days_open": 34}, {"id": "dc227ab072f4e227", "lng": 6.563011408, "lat": 52.992393013, "category": "Overlast Openbare Ruimte", "category_slug": "overlast-openbare-ruimte", "subcategory": "Overig Overlast Openbare Ruimte", "subcategory_slug": "overig-overlast-openbare-ruimte", "created_at": "2026-05-24T16:41:08.890537+00:00", "wijk": "Centrum", "address": "Brink 38", "resolved_date": "2026-06-29", "days_open": 35}, {"id": "cc09bfe2a418738e", "lng": 6.563020361, "lat": 52.992552425, "category": "Overlast Openbare Ruimte", "category_slug": "overlast-openbare-ruimte", "subcategory": "Overig Overlast Openbare Ruimte", "subcategory_slug": "overig-overlast-openbare-ruimte", "created_at": "2026-05-28T08:42:22.093875+00:00", "wijk": "Centrum", "address": "Brink 38", "resolved_date": "2026-06-29", "days_open": 31}, {"id": "ba9f5373f79ca0bc", "lng": 6.564074233, "lat": 52.993945965, "category": "Overlast Openbare Ruimte", "category_slug": "overlast-openbare-ruimte", "subcategory": "Overig Overlast Openbare Ruimte", "subcategory_slug": "overig-overlast-openbare-ruimte", "created_at": "2026-05-24T17:13:06.890651+00:00", "wijk": "Centrum", "address": "Brink 8", "resolved_date": "2026-06-29", "days_open": 35}, {"id": "1c37e5d7bc0098fd", "lng": 6.563596129, "lat": 52.993354155, "category": "Overlast Openbare Ruimte", "category_slug": "overlast-openbare-ruimte", "subcategory": "Overig Overlast Openbare Ruimte", "subcategory_slug": "overig-overlast-openbare-ruimte", "created_at": "2026-05-24T22:09:37.81509+00:00", "wijk": "Centrum", "address": "Brink 3", "resolved_date": "2026-06-29", "days_open": 35}, {"id": "c699a5bdf6abb8b5", "lng": 6.562610476, "lat": 52.993314382, "category": "Overlast Openbare Ruimte", "category_slug": "overlast-openbare-ruimte", "subcategory": "Overig Overlast Openbare Ruimte", "subcategory_slug": "overig-overlast-openbare-ruimte", "created_at": "2026-06-27T23:05:11.066611+00:00", "wijk": "Centrum", "address": "Torenlaan 2A", "resolved_date": "2026-06-29", "days_open": 1}, {"id": "21f39b853a2dc474", "lng": 6.56506708, "lat": 52.9946364, "category": "Wegen, verkeer en straatmeubilair", "category_slug": "wegen-verkeer-en-straatmeubilair", "subcategory": "Straatverlichting", "subcategory_slug": "straatverlichting", "created_at": "2026-03-10T07:34:53.290599+00:00", "wijk": "Centrum", "address": "Javastraat 13", "resolved_date": "2026-06-29", "days_open": 110}, {"id": "8a7d19acbcf52828", "lng": 6.571293258, "lat": 52.99453057, "category": "Wegen, verkeer en straatmeubilair", "category_slug": "wegen-verkeer-en-straatmeubilair", "subcategory": "Straatverlichting", "subcategory_slug": "straatverlichting", "created_at": "2026-06-22T09:41:22.973981+00:00", "wijk": "Centrum", "address": "Hendrik de Ruiterstraat 15", "resolved_date": "2026-06-29", "days_open": 6}, {"id": "1b01876dd9186bdf", "lng": 6.56995908, "lat": 52.99820573, "category": "Afval", "category_slug": "afval", "subcategory": "Container", "subcategory_slug": "container", "created_at": "2026-06-26T14:52:51.265363+00:00", "wijk": "Noorderpark", "address": "Veemarktstraat 28", "resolved_date": "2026-06-29", "days_open": 2}, {"id": "1acb46f66effd418", "lng": 6.56279547, "lat": 52.99820893, "category": "Afval", "category_slug": "afval", "subcategory": "Container", "subcategory_slug": "container", "created_at": "2026-06-26T13:55:00.775883+00:00", "wijk": "Noorderpark", "address": "Oude-Molenstraat 54", "resolved_date": "2026-06-29", "days_open": 2}, {"id": "e2937c41b5ce12c5", "lng": 6.560382843, "lat": 52.995416186, "category": "overig", "category_slug": "overig", "subcategory": "overig", "subcategory_slug": "overig", "created_at": "2026-06-17T13:30:38.582853+00:00", "wijk": "Centrum", "address": "Koopmansplein 8", "resolved_date": "2026-06-29", "days_open": 11}, {"id": "bb7050e4602dd380", "lng": 6.560380161, "lat": 52.995370008, "category": "Overlast Openbare Ruimte", "category_slug": "overlast-openbare-ruimte", "subcategory": "Overig Overlast Openbare Ruimte", "subcategory_slug": "overig-overlast-openbare-ruimte", "created_at": "2026-06-27T10:50:16.492505+00:00", "wijk": "Centrum", "address": "Koopmansplein 8", "resolved_date": "2026-06-29", "days_open": 1}, {"id": "2ae2e11e28863061", "lng": 6.560395586, "lat": 52.994910073, "category": "Afval", "category_slug": "afval", "subcategory": "Minicontainer", "subcategory_slug": "minicontainer", "created_at": "2026-06-26T14:58:07.462465+00:00", "wijk": "Centrum", "address": "Weierspoort 37", "resolved_date": "2026-06-29", "days_open": 2}, {"id": "929458b1802d6b7f", "lng": 6.559841037, "lat": 52.993502145, "category": "Overlast Openbare Ruimte", "category_slug": "overlast-openbare-ruimte", "subcategory": "Overig Overlast Openbare Ruimte", "subcategory_slug": "overig-overlast-openbare-ruimte", "created_at": "2026-04-22T14:33:08.243074+00:00", "wijk": "Centrum", "address": "Markt 11A", "resolved_date": "2026-06-29", "days_open": 67}, {"id": "4958f4a7a1db8040", "lng": 6.545976967, "lat": 52.999656736, "category": "Afval", "category_slug": "afval", "subcategory": "Dumping", "subcategory_slug": "dumping", "created_at": "2026-06-26T12:16:10.583936+00:00", "wijk": "Lariks", "address": "Selma Lagerlöflaan 3", "resolved_date": "2026-06-29", "days_open": 2}, {"id": "0ea9241f04d90956", "lng": 6.542214612, "lat": 52.998846786, "category": "Afval", "category_slug": "afval", "subcategory": "Gevaarlijk afval", "subcategory_slug": "gevaarlijk-afval", "created_at": "2026-06-27T10:45:36.571212+00:00", "wijk": "Lariks", "address": "Laak 1", "resolved_date": "2026-06-29", "days_open": 1}, {"id": "ab6f1fe82eee722f", "lng": 6.54115269, "lat": 52.99587464, "category": "Afval", "category_slug": "afval", "subcategory": "Minicontainer", "subcategory_slug": "minicontainer", "created_at": "2026-06-26T12:08:16.669208+00:00", "wijk": "Lariks", "address": "Bitse 5", "resolved_date": "2026-06-29", "days_open": 2}, {"id": "d5a0006704603da9", "lng": 6.55849725, "lat": 52.98952399, "category": "Openbaar groen en water", "category_slug": "openbaar-groen-en-water", "subcategory": "Maaien", "subcategory_slug": "maaien", "created_at": "2026-06-26T07:36:31.543051+00:00", "wijk": "Centrum", "address": "Beilerstraat 43", "resolved_date": "2026-06-29", "days_open": 2}, {"id": "fa0d0610752894c5", "lng": 6.55981477, "lat": 52.99210704, "category": "Overlast Openbare Ruimte", "category_slug": "overlast-openbare-ruimte", "subcategory": "Overig Overlast Openbare Ruimte", "subcategory_slug": "overig-overlast-openbare-ruimte", "created_at": "2026-06-25T15:06:58.613858+00:00", "wijk": "Centrum", "address": "Kerkplein 7A", "resolved_date": "2026-06-29", "days_open": 3}, {"id": "3d7fdb66d13c889f", "lng": 6.56194808, "lat": 52.990799915, "category": "Overlast Openbare Ruimte", "category_slug": "overlast-openbare-ruimte", "subcategory": "Overig Overlast Openbare Ruimte", "subcategory_slug": "overig-overlast-openbare-ruimte", "created_at": "2026-05-24T18:35:57.108504+00:00", "wijk": "Centrum", "address": "Wilhelminastraat 16", "resolved_date": "2026-06-29", "days_open": 35}, {"id": "b7142a1de2494a52", "lng": 6.56163005, "lat": 52.99076831, "category": "Overlast Openbare Ruimte", "category_slug": "overlast-openbare-ruimte", "subcategory": "Overig Overlast Openbare Ruimte", "subcategory_slug": "overig-overlast-openbare-ruimte", "created_at": "2026-06-03T07:42:35.694119+00:00", "wijk": "Centrum", "address": "Wilhelminastraat 20", "resolved_date": "2026-06-29", "days_open": 25}, {"id": "84b28b13e75c5d19", "lng": 6.556317422, "lat": 52.977316396, "category": "Wegen, verkeer en straatmeubilair", "category_slug": "wegen-verkeer-en-straatmeubilair", "subcategory": "Verkeerslicht", "subcategory_slug": "verkeerslicht", "created_at": "2026-06-27T13:03:36.689058+00:00", "wijk": "Centrum", "address": "Beilerstraat 233", "resolved_date": "2026-06-29", "days_open": 1}, {"id": "3c9d32a8645958bb", "lng": 6.55763764, "lat": 52.97854916, "category": "Wegen, verkeer en straatmeubilair", "category_slug": "wegen-verkeer-en-straatmeubilair", "subcategory": "Verkeerslicht", "subcategory_slug": "verkeerslicht", "created_at": "2026-06-27T14:17:46.595223+00:00", "wijk": "Centrum", "address": "Beilerstraat 92", "resolved_date": "2026-06-29", "days_open": 1}, {"id": "0e475819dbdcd6da", "lng": 6.53014074, "lat": 52.98550162, "category": "Openbaar groen en water", "category_slug": "openbaar-groen-en-water", "subcategory": "Maaien", "subcategory_slug": "maaien", "created_at": "2026-06-26T06:43:54.919113+00:00", "wijk": "Assen-West", "address": "De Wouden 159", "resolved_date": "2026-06-29", "days_open": 2}, {"id": "8d9bc53cc960f211", "lng": 6.517134905, "lat": 52.994913139, "category": "Openbaar groen en water", "category_slug": "openbaar-groen-en-water", "subcategory": "Boom", "subcategory_slug": "boom", "created_at": "2026-06-22T06:47:58.636172+00:00", "wijk": "Kloosterveen", "address": "Jupiterstraat 39", "resolved_date": "2026-06-29", "days_open": 6}, {"id": "3e3861e6e1ceb07f", "lng": 6.515724063, "lat": 53.007062897, "category": "Overlast Dier", "category_slug": "overlast-dier", "subcategory": "Hond", "subcategory_slug": "hond", "created_at": "2026-06-26T13:54:10.730687+00:00", "wijk": "Kloosterveen", "address": "Grote Hout 1", "resolved_date": "2026-06-28", "days_open": 1}, {"id": "39949716eed69a3f", "lng": 6.541980207, "lat": 53.00753277, "category": "Overlast Openbare Ruimte", "category_slug": "overlast-openbare-ruimte", "subcategory": "Scooter", "subcategory_slug": "scooter", "created_at": "2026-06-25T13:33:41.161874+00:00", "wijk": "Lariks", "address": "Amstelstraat 7", "resolved_date": "2026-06-28", "days_open": 2}, {"id": "5cdaae9532b6a5f2", "lng": 6.59234316, "lat": 53.02043434, "category": "Overlast Openbare Ruimte", "category_slug": "overlast-openbare-ruimte", "subcategory": "Luchtkwaliteit", "subcategory_slug": "luchtkwaliteit", "created_at": "2026-06-06T06:23:43.612426+00:00", "wijk": "Marsdijk", "address": "Vossenslag 54", "resolved_date": "2026-06-28", "days_open": 21}, {"id": "8ec79b650b73d3e5", "lng": 6.567361951, "lat": 53.001173266, "category": "Wegen, verkeer en straatmeubilair", "category_slug": "wegen-verkeer-en-straatmeubilair", "subcategory": "Speelvoorziening", "subcategory_slug": "speelvoorziening", "created_at": "2026-06-27T02:27:36.343698+00:00", "wijk": "Noorderpark", "address": "Bilderdijkplantsoen 11", "resolved_date": "2026-06-28", "days_open": 0}, {"id": "85e50c9206138688", "lng": 6.574091613, "lat": 52.975948254, "category": "Overlast Openbare Ruimte", "category_slug": "overlast-openbare-ruimte", "subcategory": "Overig Overlast Openbare Ruimte", "subcategory_slug": "overig-overlast-openbare-ruimte", "created_at": "2026-06-21T15:45:59.261876+00:00", "wijk": "Assen-Oost", "address": "Pronkridder 82", "resolved_date": "2026-06-28", "days_open": 6}, {"id": "66be3aa508d99afd", "lng": 6.566256881, "lat": 52.997340136, "category": "Overlast Openbare Ruimte", "category_slug": "overlast-openbare-ruimte", "subcategory": "Overig Overlast Openbare Ruimte", "subcategory_slug": "overig-overlast-openbare-ruimte", "created_at": "2026-06-26T10:04:34.330931+00:00", "wijk": "Noorderpark", "address": "Kloekhorststraat 33", "resolved_date": "2026-06-28", "days_open": 1}, {"id": "a0667c9c7123b0b6", "lng": 6.513122492, "lat": 52.986463137, "category": "Wegen, verkeer en straatmeubilair", "category_slug": "wegen-verkeer-en-straatmeubilair", "subcategory": "Speelvoorziening", "subcategory_slug": "speelvoorziening", "created_at": "2026-06-26T18:10:25.170842+00:00", "wijk": "Buitengebied", "address": "Baggelhuizen 7", "resolved_date": "2026-06-28", "days_open": 1}, {"id": "955a255e331ab3fa", "lng": 6.587162018, "lat": 53.015166484, "category": "Afval", "category_slug": "afval", "subcategory": "Overig Afval", "subcategory_slug": "overig-afval", "created_at": "2026-06-25T11:48:05.564189+00:00", "wijk": "Marsdijk", "address": "Roegoorn 101", "resolved_date": "2026-06-27", "days_open": 1}, {"id": "991f70dd2a6fcb3b", "lng": 6.56360695, "lat": 53.01045735, "category": "Afval", "category_slug": "afval", "subcategory": "Minicontainer", "subcategory_slug": "minicontainer", "created_at": "2026-06-26T07:00:42.199493+00:00", "wijk": "Noorderpark", "address": "Smetanalaan 37A", "resolved_date": "2026-06-27", "days_open": 0}]}